prrocr/__init__.py
prrocr/__version__.py
prrocr/pororo.py
prrocr/prrocr.py
prrocr/test.py
prrocr/utils.py
prrocr/models/__init__.py
prrocr/models/brainOCR/__init__.py
prrocr/models/brainOCR/_dataset.py
prrocr/models/brainOCR/_modules.py
prrocr/models/brainOCR/brainocr.py
prrocr/models/brainOCR/craft.py
prrocr/models/brainOCR/craft_utils.py
prrocr/models/brainOCR/detection.py
prrocr/models/brainOCR/imgproc.py
prrocr/models/brainOCR/model.py
prrocr/models/brainOCR/recognition.py
prrocr/models/brainOCR/utils.py
prrocr/models/brainOCR/modules/__init__.py
prrocr/models/brainOCR/modules/basenet.py
prrocr/models/brainOCR/modules/feature_extraction.py
prrocr/models/brainOCR/modules/prediction.py
prrocr/models/brainOCR/modules/sequence_modeling.py
prrocr/models/brainOCR/modules/transformation.py
prrocr/tasks/__init__.py
prrocr/tasks/utils/__init__.py
prrocr/tasks/utils/base.py
prrocr/tasks/utils/config.py
prrocr/tasks/utils/download_utils.py
prrocr/tasks/utils/tokenizer.py
pororo_ocr-1.0.2.dist-info/LICENSE
pororo_ocr-1.0.2.dist-info/LICENSE.3rd_party_library
pororo_ocr-1.0.2.dist-info/LICENSE.3rd_party_model
pororo_ocr-1.0.2.dist-info/METADATA
pororo_ocr-1.0.2.dist-info/WHEEL
pororo_ocr-1.0.2.dist-info/top_level.txt
pororo_ocr-1.0.2.dist-info/RECORD
