Metadata-Version: 2.1
Name: pororo-ocr
Version: 1.0.2
Summary: Rebuilding only the OCR part of the pororo package for lightweight and fast operation.
Home-page: https://github.com/stellarway/pororo-ocr
Author: Wonhee Go
Author-email: whgo.nlp@gmail.com
License: Apache-2.0
Classifier: Intended Audience :: Developers
Classifier: Intended Audience :: Science/Research
Classifier: Development Status :: 3 - Alpha
Classifier: License :: OSI Approved :: Apache Software License
Classifier: Programming Language :: Python :: 3
Classifier: Topic :: Scientific/Engineering :: Artificial Intelligence
Requires-Python: >=3.6.0
License-File: LICENSE
License-File: LICENSE.3rd_party_library
License-File: LICENSE.3rd_party_model
Requires-Dist: torch (>=1.6.0)
Requires-Dist: torchvision (>=0.7.0)
Requires-Dist: pillow (>=4.1.1)
Requires-Dist: wget
Requires-Dist: opencv-python
Requires-Dist: scikit-image
